LICENSE
MANIFEST.in
README.rst
setup.cfg
setup.py
edxclassify/__init__.py
edxclassify/chunk_parser.py
edxclassify/classifier_factory.py
edxclassify/data_cleaner_factory.py
edxclassify/feature_spec.py
edxclassify/harness.py
edxclassify/live_clf.py
edxclassify.egg-info/PKG-INFO
edxclassify.egg-info/SOURCES.txt
edxclassify.egg-info/dependency_links.txt
edxclassify.egg-info/entry_points.txt
edxclassify.egg-info/requires.txt
edxclassify.egg-info/top_level.txt
edxclassify/classifiers/__init__.py
edxclassify/classifiers/abstract_classifier.py
edxclassify/classifiers/clf_util.py
edxclassify/classifiers/custom_token_patterns.py
edxclassify/classifiers/custom_vocab.py
edxclassify/classifiers/feature_generation.py
edxclassify/classifiers/sklearn_clf.py
edxclassify/classifiers/word_lists.py
edxclassify/data_cleaners/__init__.py
edxclassify/data_cleaners/abstract_data_cleaner.py
edxclassify/data_cleaners/dc_util.py
edxclassify/data_cleaners/edx.py
edxclassify/data_cleaners/edx_answer.py
edxclassify/data_cleaners/edx_confusion.py
edxclassify/data_cleaners/edx_opinion.py
edxclassify/data_cleaners/edx_question.py
edxclassify/data_cleaners/edx_sentiment.py
edxclassify/data_cleaners/edx_urgency.py
edxclassify/saved_clf/confusion_nontechnical/confusion_nontechnical.pkl
edxclassify/saved_clf/confusion_nontechnical/confusion_nontechnical.pkl_01.npy
edxclassify/saved_clf/confusion_nontechnical/confusion_nontechnical.pkl_02.npy
edxclassify/saved_clf/confusion_nontechnical/confusion_nontechnical.pkl_03.npy
edxclassify/saved_clf/confusion_nontechnical/confusion_nontechnical.pkl_04.npy
edxclassify/saved_clf/confusion_nontechnical/confusion_nontechnical.pkl_05.npy
edxclassify/saved_clf/confusion_nontechnical/confusion_nontechnical.pkl_06.npy
edxclassify/saved_clf/confusion_nontechnical/confusion_nontechnical.pkl_07.npy
edxclassify/saved_clf/confusion_nontechnical/confusion_nontechnical.pkl_08.npy
edxclassify/saved_clf/confusion_nontechnical/confusion_nontechnical.pkl_09.npy
edxclassify/saved_clf/confusion_nontechnical/confusion_nontechnical.pkl_10.npy
edxclassify/saved_clf/confusion_nontechnical/confusion_nontechnical.pkl_11.npy
