Metadata-Version: 1.1
Name: edxclassify
Version: 0.10.a1
Summary: A machine learning workflow, with classifiers to detect                affect in MOOC discussion forums.
Home-page: https://github.com/akshayka/edxclassify
Author: Akshay Agrawal, Shane Leonard
Author-email: akshayka@cs.stanford.edu, shanel@stanford.edu
License: GNU General Public License v2
Keywords: machine-learning classification education mooc moocs forum              discussion
Platform: UNKNOWN
Classifier: Development Status :: 3 - Alpha
Classifier: Intended Audience :: Developers
Classifier: Topic :: Scientific/Engineering :: Artificial Intelligence
Classifier: License :: OSI Approved :: GNU General Public License v2 (GPLv2)
Classifier: Programming Language :: Python :: 2
Classifier: Programming Language :: Python :: 2.6
Classifier: Programming Language :: Python :: 2.7
